{"name":"maiden_voyage","maxBlock":7,"BPM":174,"offset":0,"notes":[{"LPB":4,"num":64,"block":6,"type":2,"notes":[{"LPB":4,"num":72,"block":6,"type":2,"notes":[]}]},{"LPB":4,"num":76,"block":5,"type":2,"notes":[{"LPB":4,"num":92,"block":5,"type":2,"notes":[]}]},{"LPB":4,"num":96,"block":0,"type":2,"notes":[{"LPB":4,"num":104,"block":0,"type":2,"notes":[]}]},{"LPB":4,"num":108,"block":1,"type":2,"notes":[{"LPB":4,"num":124,"block":1,"type":2,"notes":[]}]},{"LPB":4,"num":128,"block":6,"type":2,"notes":[{"LPB":4,"num":136,"block":6,"type":2,"notes":[]}]},{"LPB":4,"num":128,"block":4,"type":2,"notes":[{"LPB":4,"num":136,"block":4,"type":2,"notes":[]}]},{"LPB":4,"num":140,"block":5,"type":2,"notes":[{"LPB":4,"num":156,"block":5,"type":2,"notes":[]}]},{"LPB":4,"num":140,"block":3,"type":2,"notes":[{"LPB":4,"num":156,"block":3,"type":2,"notes":[]}]},{"LPB":4,"num":160,"block":0,"type":2,"notes":[{"LPB":4,"num":168,"block":0,"type":2,"notes":[]}]},{"LPB":4,"num":160,"block":2,"type":2,"notes":[{"LPB":4,"num":168,"block":2,"type":2,"notes":[]}]},{"LPB":4,"num":172,"block":1,"type":2,"notes":[{"LPB":4,"num":188,"block":1,"type":2,"notes":[]}]},{"LPB":4,"num":172,"block":3,"type":2,"notes":[{"LPB":4,"num":184,"block":4,"type":2,"notes":[]}]},{"LPB":4,"num":186,"block":4,"type":1,"notes":[]},{"LPB":4,"num":192,"block":0,"type":3,"notes":[]},{"LPB":4,"num":196,"block":1,"type":3,"notes":[]},{"LPB":4,"num":200,"block":2,"type":3,"notes":[]},{"LPB":4,"num":204,"block":3,"type":3,"notes":[]},{"LPB":4,"num":208,"block":6,"type":3,"notes":[]},{"LPB":4,"num":212,"block":5,"type":3,"notes":[]},{"LPB":4,"num":216,"block":4,"type":3,"notes":[]},{"LPB":4,"num":220,"block":3,"type":3,"notes":[]},{"LPB":4,"num":224,"block":0,"type":1,"notes":[]},{"LPB":4,"num":228,"block":1,"type":1,"notes":[]},{"LPB":4,"num":232,"block":2,"type":1,"notes":[]},{"LPB":4,"num":236,"block":3,"type":1,"notes":[]},{"LPB":4,"num":240,"block":6,"type":1,"notes":[]},{"LPB":4,"num":244,"block":5,"type":1,"notes":[]},{"LPB":4,"num":248,"block":4,"type":1,"notes":[]},{"LPB":4,"num":252,"block":3,"type":1,"notes":[]}]}